mce_ragas_adapter/__init__.py
mce_ragas_adapter/adapter.py
mce_ragas_adapter/metric_configuration.py
mce_ragas_adapter/metric_test_case_creation.py
mce_ragas_adapter/model_loader.py
mce_ragas_adapter-0.1.1.dist-info/METADATA
mce_ragas_adapter-0.1.1.dist-info/WHEEL
mce_ragas_adapter-0.1.1.dist-info/entry_points.txt
mce_ragas_adapter-0.1.1.dist-info/RECORD
